libname/__init__.py
libname/sms.py
otpcheck-0.0.1.dist-info/METADATA
otpcheck-0.0.1.dist-info/WHEEL
otpcheck-0.0.1.dist-info/top_level.txt
otpcheck-0.0.1.dist-info/RECORD
