Metadata-Version: 2.1
Name: otpcheck
Version: 0.0.1
Summary: Package to check OTP
Home-page: UNKNOWN
Author: Captain Cactus
Author-email: aswinmenon22@gmail.com
License: UNKNOWN
Keywords: python,otp,otp check,otp checker,otp validate,sms
Platform: UNKNOWN
Classifier: Development Status :: 1 - Planning
Classifier: Intended Audience :: Developers
Classifier: Programming Language :: Python :: 3
Classifier: Operating System :: Unix
Classifier: Operating System :: MacOS :: MacOS X
Classifier: Operating System :: Microsoft :: Windows
